waverider_generator/__init__.py
waverider_generator/curves.py
waverider_generator/flowfield.py
waverider_generator/generator.py
waverider_generator/input_validation.py
waverider_generator-3.0.1.dist-info/licenses/LICENSE
waverider_generator-3.0.1.dist-info/METADATA
waverider_generator-3.0.1.dist-info/WHEEL
waverider_generator-3.0.1.dist-info/top_level.txt
waverider_generator-3.0.1.dist-info/RECORD
