Metadata-Version: 2.4
Name: waverider_generator
Version: 3.0.1
Summary: Hypersonic Waverider Generator
Home-page: https://github.com/jade5638/waverider_generator
Author: Jade Nassif
Author-email: jade.nassif2002@gmail.com
Keywords: python,waverider,CAD,hypersonic,aerospace-engineering,osculating-cone
License-File: LICENSE
Requires-Dist: numpy
Requires-Dist: cadquery
Requires-Dist: scipy
Dynamic: author
Dynamic: author-email
Dynamic: description
Dynamic: description-content-type
Dynamic: home-page
Dynamic: keywords
Dynamic: license-file
Dynamic: requires-dist
Dynamic: summary
